[{"end":"2022-09-06 16:09:58 +0200 CEST","from":1,"label":"Traffic","properties":{"Count":[{"Start":"1993-01-21 21:37:29 +0100 CET","End":"2011-07-05 14:17:55 +0200 CEST","Value":77}],"IPv4/IPv6":[{"Start":"2005-03-13 23:14:15 +0100 CET","End":"2022-09-18 16:59:09 +0200 CEST","Value":"hiGURPbnu"}],"Risc":[{"Start":"1977-12-12 05:13:37 +0100 CET","End":"1983-02-14 14:40:27 +0100 CET","Value":91}],"TCP/UDP":[{"Start":"1999-09-16 10:37:21 +0200 CEST","End":"1999-11-04 05:19:53 +0100 CET","Value":"PnBkvaO"}]},"relationid":0,"start":"2000-01-20 06:55:28 +0100 CET","to":3},{"end":"1979-11-03 13:47:33 +0100 CET","from":1,"label":"Traffic","properties":{"Count":[{"Start":"2021-11-25 16:50:14 +0100 CET","End":"2019-01-28 20:59:00 +0100 CET","Value":81}],"IPv4/IPv6":[{"Start":"1996-02-09 06:56:55 +0100 CET","End":"1973-04-20 11:38:52 +0100 CET","Value":"uiGFBUw"}],"Risc":[{"Start":"2005-06-23 14:34:39 +0200 CEST","End":"2018-10-04 21:18:01 +0200 CEST","Value":97}],"TCP/UDP":[{"Start":"2007-08-08 20:19:40 +0200 CEST","End":"1979-07-05 12:13:13 +0100 CET","Value":"iNl"}]},"relationid":1,"start":"1989-12-01 13:13:26 +0100 CET","to":3},{"end":"1987-05-20 08:30:30 +0200 CEST","from":0,"label":"Traffic","properties":{"Count":[{"Start":"1987-01-18 11:44:06 +0100 CET","End":"2014-01-19 07:55:47 +0100 CET","Value":35}],"IPv4/IPv6":[{"Start":"2016-06-07 00:41:13 +0200 CEST","End":"1977-04-27 04:01:17 +0100 CET","Value":"NzqNOpun"}],"Risc":[{"Start":"2008-04-24 21:00:43 +0200 CEST","End":"1999-11-17 18:41:38 +0100 CET","Value":20}],"TCP/UDP":[{"Start":"2005-08-19 11:01:03 +0200 CEST","End":"2012-10-03 02:48:13 +0200 CEST","Value":"xJH"}]},"relationid":2,"start":"1991-02-15 07:44:03 +0100 CET","to":0},{"end":"1991-03-10 11:02:50 +0100 CET","from":1,"label":"Traffic","properties":{"Count":[{"Start":"2001-02-27 10:42:22 +0100 CET","End":"1997-08-27 11:58:16 +0200 CEST","Value":48}],"IPv4/IPv6":[{"Start":"2002-07-21 20:01:56 +0200 CEST","End":"2018-03-16 12:41:16 +0100 CET","Value":"lWc"}],"Risc":[{"Start":"1998-12-04 23:29:10 +0100 CET","End":"2006-11-21 06:55:06 +0100 CET","Value":95}],"TCP/UDP":[{"Start":"2003-08-19 12:06:42 +0200 CEST","End":"1973-10-08 09:39:33 +0100 CET","Value":"KyjLp"}]},"relationid":3,"start":"2016-05-17 05:32:58 +0200 CEST","to":0},{"end":"1999-11-03 06:02:10 +0100 CET","from":0,"label":"Traffic","properties":{"Count":[{"Start":"2005-11-20 11:30:44 +0100 CET","End":"1975-04-08 22:31:51 +0100 CET","Value":99}],"IPv4/IPv6":[{"Start":"1988-02-08 08:16:29 +0100 CET","End":"2005-05-25 16:15:49 +0200 CEST","Value":"XOKWcvrHQ"}],"Risc":[{"Start":"2009-11-21 17:45:39 +0100 CET","End":"1979-12-02 05:37:28 +0100 CET","Value":68}],"TCP/UDP":[{"Start":"1986-03-30 22:32:31 +0200 CEST","End":"1975-10-19 07:55:14 +0100 CET","Value":"VULqqvPhK"}]},"relationid":4,"start":"1996-08-11 09:42:07 +0200 CEST","to":4},{"end":"1980-02-17 05:29:09 +0100 CET","from":3,"label":"Traffic","properties":{"Count":[{"Start":"1992-06-19 02:06:01 +0200 CEST","End":"2000-08-23 03:01:57 +0200 CEST","Value":37}],"IPv4/IPv6":[{"Start":"1975-09-04 17:44:58 +0100 CET","End":"2002-05-17 10:51:40 +0200 CEST","Value":"SIwsrLAgg"}],"Risc":[{"Start":"1977-06-28 22:25:07 +0100 CET","End":"1988-02-14 17:52:58 +0100 CET","Value":15}],"TCP/UDP":[{"Start":"2009-05-26 08:21:01 +0200 CEST","End":"1981-03-01 06:51:24 +0100 CET","Value":"MSLjD"}]},"relationid":5,"start":"2000-01-23 05:13:11 +0100 CET","to":2},{"end":"1998-07-31 08:06:37 +0200 CEST","from":0,"label":"Traffic","properties":{"Count":[{"Start":"2006-03-30 00:31:09 +0200 CEST","End":"2001-12-24 13:11:02 +0100 CET","Value":64}],"IPv4/IPv6":[{"Start":"2009-01-01 05:58:18 +0100 CET","End":"1973-01-26 14:03:31 +0100 CET","Value":"sKYTuDC"}],"Risc":[{"Start":"1984-04-28 12:28:16 +0200 CEST","End":"1978-08-17 18:49:24 +0100 CET","Value":78}],"TCP/UDP":[{"Start":"1989-09-12 20:43:15 +0200 CEST","End":"1997-11-28 13:16:11 +0100 CET","Value":"TMmfckIUo"}]},"relationid":6,"start":"2012-04-02 00:58:10 +0200 CEST","to":2},{"end":"2001-04-19 17:40:44 +0200 CEST","from":2,"label":"Traffic","properties":{"Count":[{"Start":"2019-06-11 00:07:01 +0200 CEST","End":"1986-08-05 17:03:21 +0200 CEST","Value":27}],"IPv4/IPv6":[{"Start":"2008-11-22 23:36:56 +0100 CET","End":"1985-11-23 03:35:25 +0100 CET","Value":"ubRWinc"}],"Risc":[{"Start":"1988-07-28 08:04:10 +0200 CEST","End":"1995-07-02 15:10:34 +0200 CEST","Value":85}],"TCP/UDP":[{"Start":"1999-10-11 20:56:11 +0200 CEST","End":"1991-09-21 04:34:00 +0200 CEST","Value":"JCYPPcB"}]},"relationid":7,"start":"2016-06-05 13:35:24 +0200 CEST","to":0},{"end":"1979-01-20 17:07:24 +0100 CET","from":0,"label":"Traffic","properties":{"Count":[{"Start":"1992-11-26 18:20:32 +0100 CET","End":"1975-10-15 00:02:01 +0100 CET","Value":8}],"IPv4/IPv6":[{"Start":"2005-01-27 19:37:19 +0100 CET","End":"1986-07-01 17:42:22 +0200 CEST","Value":"omChoYSTl"}],"Risc":[{"Start":"1994-06-15 10:29:30 +0200 CEST","End":"2002-09-25 22:13:41 +0200 CEST","Value":91}],"TCP/UDP":[{"Start":"1983-05-26 18:31:08 +0200 CEST","End":"1996-06-11 10:28:42 +0200 CEST","Value":"kDoHAdyaQ"}]},"relationid":8,"start":"1993-09-07 23:45:25 +0200 CEST","to":2},{"end":"1974-07-09 19:53:39 +0100 CET","from":4,"label":"Traffic","properties":{"Count":[{"Start":"1998-07-03 10:59:48 +0200 CEST","End":"2020-09-25 06:49:08 +0200 CEST","Value":96}],"IPv4/IPv6":[{"Start":"1975-08-02 04:28:52 +0100 CET","End":"1986-10-05 16:59:11 +0100 CET","Value":"IaUcrM"}],"Risc":[{"Start":"1989-02-05 13:50:40 +0100 CET","End":"1974-09-29 02:20:57 +0100 CET","Value":8}],"TCP/UDP":[{"Start":"1977-10-19 11:30:34 +0100 CET","End":"2006-06-07 06:05:11 +0200 CEST","Value":"wBIVrk"}]},"relationid":9,"start":"1982-03-31 01:56:58 +0200 CEST","to":2},{"end":"1980-01-24 10:41:35 +0100 CET","from":3,"label":"Traffic","properties":{"Count":[{"Start":"1997-07-23 07:13:31 +0200 CEST","End":"1989-10-17 15:59:26 +0100 CET","Value":26}],"IPv4/IPv6":[{"Start":"1981-07-22 14:18:54 +0200 CEST","End":"1980-11-14 18:43:22 +0100 CET","Value":"LrmQAd"}],"Risc":[{"Start":"1976-04-13 04:17:45 +0100 CET","End":"1994-09-21 14:09:51 +0200 CEST","Value":53}],"TCP/UDP":[{"Start":"1989-07-11 15:52:34 +0200 CEST","End":"1981-07-26 18:58:01 +0200 CEST","Value":"SgGGaWzvh"}]},"relationid":10,"start":"2016-03-09 14:49:00 +0100 CET","to":112},{"end":"1993-01-26 20:07:12 +0100 CET","from":0,"label":"Traffic","properties":{"Count":[{"Start":"2007-04-06 20:32:19 +0200 CEST","End":"2003-07-05 20:13:38 +0200 CEST","Value":47}],"IPv4/IPv6":[{"Start":"1979-04-26 18:26:09 +0100 CET","End":"1995-10-27 22:14:44 +0100 CET","Value":"PCn"}],"Risc":[{"Start":"2009-10-26 18:54:25 +0100 CET","End":"1987-10-04 01:18:03 +0100 CET","Value":65}],"TCP/UDP":[{"Start":"1987-07-27 03:31:24 +0200 CEST","End":"1987-07-31 02:49:41 +0200 CEST","Value":"BOHckd"}]},"relationid":11,"start":"1987-06-06 09:28:41 +0200 CEST","to":81},{"end":"1978-07-21 22:20:39 +0100 CET","from":0,"label":"Traffic","properties":{"Count":[{"Start":"2012-10-17 21:41:59 +0200 CEST","End":"2007-12-23 04:23:11 +0100 CET","Value":49}],"IPv4/IPv6":[{"Start":"2019-02-24 02:29:51 +0100 CET","End":"2016-09-19 23:15:12 +0200 CEST","Value":"Zzsbqw"}],"Risc":[{"Start":"2012-02-03 18:28:33 +0100 CET","End":"2006-07-04 10:13:43 +0200 CEST","Value":30}],"TCP/UDP":[{"Start":"2018-06-29 21:35:37 +0200 CEST","End":"1986-04-04 14:35:13 +0200 CEST","Value":"SGTTsTI"}]},"relationid":12,"start":"1977-09-06 21:26:14 +0100 CET","to":54},{"end":"1977-10-01 05:26:11 +0100 CET","from":4,"label":"Traffic","properties":{"Count":[{"Start":"1986-03-24 17:44:16 +0100 CET","End":"2007-10-03 09:24:08 +0200 CEST","Value":25}],"IPv4/IPv6":[{"Start":"2006-08-05 05:30:51 +0200 CEST","End":"2006-07-10 02:07:53 +0200 CEST","Value":"kAOnxFGm"}],"Risc":[{"Start":"1999-04-16 23:22:05 +0200 CEST","End":"1980-10-29 18:13:15 +0100 CET","Value":43}],"TCP/UDP":[{"Start":"2013-07-31 08:14:25 +0200 CEST","End":"1995-01-18 03:39:30 +0100 CET","Value":"docHscb"}]},"relationid":13,"start":"1976-05-16 16:41:49 +0100 CET","to":74},{"end":"1995-09-26 09:12:55 +0100 CET","from":3,"label":"Traffic","properties":{"Count":[{"Start":"2010-10-09 09:03:06 +0200 CEST","End":"2002-02-22 19:15:25 +0100 CET","Value":56}],"IPv4/IPv6":[{"Start":"1983-09-21 22:17:50 +0200 CEST","End":"2020-02-21 04:57:57 +0100 CET","Value":"PIxSneY"}],"Risc":[{"Start":"2020-04-14 18:10:23 +0200 CEST","End":"1991-05-16 10:59:58 +0200 CEST","Value":97}],"TCP/UDP":[{"Start":"2013-07-19 14:01:24 +0200 CEST","End":"2019-05-01 01:10:57 +0200 CEST","Value":"MQA"}]},"relationid":14,"start":"2008-03-11 10:26:29 +0100 CET","to":27},{"end":"1990-03-23 23:07:41 +0100 CET","from":0,"label":"Traffic","properties":{"Count":[{"Start":"1983-07-12 18:31:43 +0200 CEST","End":"1990-08-17 20:41:56 +0200 CEST","Value":6}],"IPv4/IPv6":[{"Start":"1975-06-29 20:50:41 +0100 CET","End":"1994-11-01 05:05:48 +0100 CET","Value":"PBNfRQZvw"}],"Risc":[{"Start":"1976-04-08 19:34:26 +0100 CET","End":"2002-02-22 03:05:53 +0100 CET","Value":81}],"TCP/UDP":[{"Start":"1985-11-04 13:12:03 +0100 CET","End":"1990-06-26 11:02:08 +0200 CEST","Value":"ZllFVm"}]},"relationid":15,"start":"1974-09-30 05:04:36 +0100 CET","to":41},{"end":"2000-06-25 06:19:57 +0200 CEST","from":3,"label":"Traffic","properties":{"Count":[{"Start":"2022-11-16 02:32:49 +0100 CET","End":"1998-11-14 11:48:06 +0100 CET","Value":58}],"IPv4/IPv6":[{"Start":"2008-07-27 01:51:43 +0200 CEST","End":"1994-08-04 03:23:03 +0200 CEST","Value":"Gzx"}],"Risc":[{"Start":"1987-08-10 04:59:57 +0200 CEST","End":"2015-05-13 20:14:08 +0200 CEST","Value":33}],"TCP/UDP":[{"Start":"2001-04-20 06:59:11 +0200 CEST","End":"1984-07-21 06:15:25 +0200 CEST","Value":"qpEm"}]},"relationid":16,"start":"1982-08-01 01:18:23 +0200 CEST","to":91},{"end":"1993-04-27 01:59:09 +0200 CEST","from":2,"label":"Traffic","properties":{"Count":[{"Start":"1993-12-18 18:57:45 +0100 CET","End":"2010-08-14 06:19:24 +0200 CEST","Value":75}],"IPv4/IPv6":[{"Start":"2020-03-06 01:21:37 +0100 CET","End":"1978-07-20 05:57:17 +0100 CET","Value":"XMHT"}],"Risc":[{"Start":"2013-06-15 22:13:44 +0200 CEST","End":"1975-07-08 22:26:31 +0100 CET","Value":55}],"TCP/UDP":[{"Start":"1993-02-07 02:59:41 +0100 CET","End":"1998-04-14 02:32:33 +0200 CEST","Value":"NXn"}]},"relationid":17,"start":"1982-02-23 05:56:24 +0100 CET","to":80},{"end":"1998-02-15 14:16:09 +0100 CET","from":0,"label":"Traffic","properties":{"Count":[{"Start":"1996-06-28 09:57:25 +0200 CEST","End":"1994-01-10 07:05:06 +0100 CET","Value":32}],"IPv4/IPv6":[{"Start":"2009-03-29 17:33:09 +0200 CEST","End":"2007-05-05 21:16:34 +0200 CEST","Value":"ByQTuAFNB"}],"Risc":[{"Start":"2019-08-02 18:44:32 +0200 CEST","End":"2011-12-28 15:47:28 +0100 CET","Value":55}],"TCP/UDP":[{"Start":"1973-04-29 20:33:09 +0100 CET","End":"1998-03-24 00:01:57 +0100 CET","Value":"fkST"}]},"relationid":18,"start":"1990-02-10 00:20:36 +0100 CET","to":106},{"end":"2009-08-30 10:41:14 +0200 CEST","from":2,"label":"Traffic","properties":{"Count":[{"Start":"2002-07-04 18:49:43 +0200 CEST","End":"1992-08-07 20:12:30 +0200 CEST","Value":10}],"IPv4/IPv6":[{"Start":"1979-05-21 08:23:11 +0100 CET","End":"1986-10-19 07:13:58 +0100 CET","Value":"nqO"}],"Risc":[{"Start":"1973-04-11 05:20:13 +0100 CET","End":"1990-08-28 23:39:55 +0200 CEST","Value":45}],"TCP/UDP":[{"Start":"1981-09-28 18:52:25 +0100 CET","End":"1978-09-13 21:11:55 +0100 CET","Value":"UyatZTp"}]},"relationid":19,"start":"1993-05-20 07:08:34 +0200 CEST","to":94},{"end":"1991-10-22 04:37:19 +0100 CET","from":0,"label":"Traffic","properties":{"Count":[{"Start":"2008-05-28 07:58:47 +0200 CEST","End":"2017-05-15 12:28:54 +0200 CEST","Value":13}],"IPv4/IPv6":[{"Start":"1994-03-06 20:40:40 +0100 CET","End":"2020-11-03 02:30:52 +0100 CET","Value":"wiHbvgC"}],"Risc":[{"Start":"1997-09-26 15:15:45 +0200 CEST","End":"2013-02-10 15:38:19 +0100 CET","Value":30}],"TCP/UDP":[{"Start":"2019-03-18 21:29:24 +0100 CET","End":"1976-08-19 17:54:16 +0100 CET","Value":"kev"}]},"relationid":20,"start":"1985-01-19 05:27:03 +0100 CET","to":8},{"end":"2009-01-25 13:50:11 +0100 CET","from":4,"label":"Traffic","properties":{"Count":[{"Start":"1983-10-08 18:18:30 +0100 CET","End":"1990-07-14 07:30:40 +0200 CEST","Value":84}],"IPv4/IPv6":[{"Start":"1980-09-11 09:55:14 +0200 CEST","End":"1993-02-05 17:05:16 +0100 CET","Value":"LIdvhQqnl"}],"Risc":[{"Start":"1976-07-28 10:03:17 +0100 CET","End":"2007-05-23 11:36:26 +0200 CEST","Value":84}],"TCP/UDP":[{"Start":"1978-04-27 23:11:31 +0100 CET","End":"2020-05-27 04:13:48 +0200 CEST","Value":"VRHpki"}]},"relationid":21,"start":"1989-04-23 03:45:09 +0200 CEST","to":11},{"end":"2006-02-23 11:23:37 +0100 CET","from":0,"label":"Traffic","properties":{"Count":[{"Start":"2012-05-20 22:59:58 +0200 CEST","End":"2017-12-15 22:22:01 +0100 CET","Value":42}],"IPv4/IPv6":[{"Start":"1989-04-29 20:08:20 +0200 CEST","End":"2005-04-22 22:06:45 +0200 CEST","Value":"fSQnxr"}],"Risc":[{"Start":"1992-09-23 23:18:03 +0200 CEST","End":"2002-11-05 00:42:23 +0100 CET","Value":66}],"TCP/UDP":[{"Start":"2018-10-16 08:43:12 +0200 CEST","End":"1976-07-04 21:50:42 +0100 CET","Value":"nxDgF"}]},"relationid":22,"start":"1989-06-19 13:48:44 +0200 CEST","to":11},{"end":"1982-03-31 10:01:48 +0200 CEST","from":1,"label":"Traffic","properties":{"Count":[{"Start":"2002-05-01 00:49:27 +0200 CEST","End":"2010-12-14 22:19:06 +0100 CET","Value":80}],"IPv4/IPv6":[{"Start":"1998-08-11 03:20:39 +0200 CEST","End":"1993-08-02 02:01:41 +0200 CEST","Value":"iyBKYBH"}],"Risc":[{"Start":"2020-05-08 21:12:52 +0200 CEST","End":"2021-11-05 15:18:56 +0100 CET","Value":27}],"TCP/UDP":[{"Start":"1976-11-11 23:24:46 +0100 CET","End":"1990-10-18 05:58:21 +0100 CET","Value":"wsu"}]},"relationid":23,"start":"2020-12-11 09:01:11 +0100 CET","to":14},{"end":"1995-05-05 14:09:32 +0200 CEST","from":0,"label":"Traffic","properties":{"Count":[{"Start":"1991-09-10 23:38:52 +0200 CEST","End":"1990-10-25 02:28:22 +0100 CET","Value":2}],"IPv4/IPv6":[{"Start":"1974-10-21 23:59:42 +0100 CET","End":"2013-04-11 16:19:46 +0200 CEST","Value":"bCgbnlJ"}],"Risc":[{"Start":"2017-03-25 07:52:41 +0100 CET","End":"1975-10-01 06:44:21 +0100 CET","Value":41}],"TCP/UDP":[{"Start":"2008-06-20 06:36:45 +0200 CEST","End":"1991-12-26 16:30:02 +0100 CET","Value":"cjgW"}]},"relationid":24,"start":"1988-07-11 09:29:45 +0200 CEST","to":10},{"end":"1992-05-11 14:17:31 +0200 CEST","from":3,"label":"Traffic","properties":{"Count":[{"Start":"2018-09-30 23:12:21 +0200 CEST","End":"2007-07-08 08:51:36 +0200 CEST","Value":85}],"IPv4/IPv6":[{"Start":"1995-03-24 02:46:47 +0100 CET","End":"1987-09-26 23:52:41 +0200 CEST","Value":"PCcppfowu"}],"Risc":[{"Start":"1993-04-24 18:58:11 +0200 CEST","End":"1977-08-31 06:20:10 +0100 CET","Value":7}],"TCP/UDP":[{"Start":"2004-02-24 09:26:23 +0100 CET","End":"1978-03-25 00:27:51 +0100 CET","Value":"PegdGvPgR"}]},"relationid":25,"start":"2017-01-13 02:24:34 +0100 CET","to":13},{"end":"2022-12-05 20:48:46 +0100 CET","from":1,"label":"Traffic","properties":{"Count":[{"Start":"2000-02-01 23:59:03 +0100 CET","End":"2001-02-02 14:48:05 +0100 CET","Value":23}],"IPv4/IPv6":[{"Start":"2022-03-27 04:25:00 +0200 CEST","End":"2014-03-06 13:34:39 +0100 CET","Value":"BVQURATpa"}],"Risc":[{"Start":"1992-03-16 21:24:03 +0100 CET","End":"2021-08-02 14:41:30 +0200 CEST","Value":96}],"TCP/UDP":[{"Start":"1998-09-29 23:37:25 +0200 CEST","End":"1977-02-05 02:39:47 +0100 CET","Value":"SUuSZN"}]},"relationid":26,"start":"1979-02-18 12:14:40 +0100 CET","to":7},{"end":"1977-12-11 19:45:50 +0100 CET","from":2,"label":"Traffic","properties":{"Count":[{"Start":"2017-04-03 20:33:34 +0200 CEST","End":"1980-04-06 07:15:48 +0200 CEST","Value":59}],"IPv4/IPv6":[{"Start":"2014-12-25 20:15:48 +0100 CET","End":"2022-02-25 08:22:01 +0100 CET","Value":"saHC"}],"Risc":[{"Start":"2011-10-23 18:44:04 +0200 CEST","End":"1977-10-16 12:31:50 +0100 CET","Value":23}],"TCP/UDP":[{"Start":"2017-12-12 18:38:51 +0100 CET","End":"1990-08-22 16:19:29 +0200 CEST","Value":"RgCZ"}]},"relationid":27,"start":"1992-10-04 22:44:42 +0100 CET","to":10},{"end":"2003-01-05 15:56:55 +0100 CET","from":4,"label":"Traffic","properties":{"Count":[{"Start":"1981-09-24 01:35:19 +0200 CEST","End":"2009-05-12 10:36:52 +0200 CEST","Value":85}],"IPv4/IPv6":[{"Start":"2015-01-09 12:19:52 +0100 CET","End":"1981-06-06 08:17:02 +0200 CEST","Value":"FkHfDL"}],"Risc":[{"Start":"2005-05-02 00:33:30 +0200 CEST","End":"2001-06-06 21:09:40 +0200 CEST","Value":99}],"TCP/UDP":[{"Start":"1988-10-03 17:44:29 +0100 CET","End":"2005-09-23 10:43:33 +0200 CEST","Value":"ZpMYNf"}]},"relationid":28,"start":"1979-02-12 09:40:20 +0100 CET","to":10},{"end":"1995-06-01 17:23:43 +0200 CEST","from":1,"label":"Traffic","properties":{"Count":[{"Start":"2004-05-23 07:25:23 +0200 CEST","End":"1998-02-18 09:09:25 +0100 CET","Value":31}],"IPv4/IPv6":[{"Start":"1981-03-14 06:59:15 +0100 CET","End":"1976-07-24 12:49:20 +0100 CET","Value":"OxvHW"}],"Risc":[{"Start":"1990-09-04 05:10:35 +0200 CEST","End":"2003-11-20 11:17:22 +0100 CET","Value":38}],"TCP/UDP":[{"Start":"1974-03-08 20:37:51 +0100 CET","End":"1998-01-23 14:55:17 +0100 CET","Value":"jdWZ"}]},"relationid":29,"start":"1979-12-31 08:21:49 +0100 CET","to":11}]
